mlbootstrap/tf/__init__.py
mlbootstrap/tf/model.py
mlbootstrap_tf-0.0.5.dist-info/METADATA
mlbootstrap_tf-0.0.5.dist-info/RECORD
mlbootstrap_tf-0.0.5.dist-info/WHEEL
mlbootstrap_tf-0.0.5.dist-info/top_level.txt
